setup.py
nch_distributions/Binomialdistribution.py
nch_distributions/Gaussiandistribution.py
nch_distributions/Generaldistribution.py
nch_distributions/__init__.py
nch_distributions.egg-info/PKG-INFO
nch_distributions.egg-info/SOURCES.txt
nch_distributions.egg-info/dependency_links.txt
nch_distributions.egg-info/not-zip-safe
nch_distributions.egg-info/top_level.txt