Metadata-Version: 1.0
Name: nch-distributions
Version: 0.4
Summary: Gaussian distributions
Home-page: UNKNOWN
Author: NCH
Author-email: UNKNOWN
License: UNKNOWN
Platform: UNKNOWN
